crunch_uml/__init__.py
crunch_uml/cli.py
crunch_uml/const.py
crunch_uml/db.py
crunch_uml/exceptions.py
crunch_uml/lang.py
crunch_uml/py.typed
crunch_uml/registry.py
crunch_uml/schema.py
crunch_uml/util.py
crunch_uml/parsers/__init__.py
crunch_uml/parsers/eaxmiparser.py
crunch_uml/parsers/multiple_parsers.py
crunch_uml/parsers/parser.py
crunch_uml/parsers/xmiparser.py
crunch_uml/renderers/__init__.py
crunch_uml/renderers/earepoupdater.py
crunch_uml/renderers/jinja2renderer.py
crunch_uml/renderers/lodrenderer copy.py
crunch_uml/renderers/lodrenderer.py
crunch_uml/renderers/pandasrenderer.py
crunch_uml/renderers/renderer.py
crunch_uml/renderers/sqlarenderer.py
crunch_uml/renderers/xlsxrenderer.py
crunch_uml/templates/__init__.py
crunch_uml/templates/ddas_markdown.j2
crunch_uml/templates/ggm_markdown.j2
crunch_uml/templates/ggm_sqlalchemy.j2
crunch_uml/templates/json_datatypes.json
crunch_uml/templates/json_schema.j2
crunch_uml/transformers/__init__.py
crunch_uml/transformers/copytransformer.py
crunch_uml/transformers/plugin.py
crunch_uml/transformers/plugintransformer.py
crunch_uml/transformers/transformer.py
crunch_uml-0.4.4.dist-info/licenses/LICENSE
crunch_uml-0.4.4.dist-info/METADATA
crunch_uml-0.4.4.dist-info/WHEEL
crunch_uml-0.4.4.dist-info/entry_points.txt
crunch_uml-0.4.4.dist-info/top_level.txt
crunch_uml-0.4.4.dist-info/RECORD
