Metadata-Version: 2.4
Name: crunch_uml
Version: 0.4.4
Summary: Crunch_uml reads UML Class model from multiple formats (including XMI, Enterprise Architect XMI, Excel, Json, and others), can perform transformations and renders them to other formats (including Markdown, json, json schema and many others).
Home-page: http://github.com/brienen/crunch_uml
Author: Arjen Brienen
License: MIT
Classifier: Programming Language :: Python :: 3
Classifier: License :: OSI Approved :: MIT License
Classifier: Operating System :: OS Independent
Requires-Python: >=3.9, <3.13
License-File: LICENSE
Requires-Dist: SQLAlchemy<3,>=2.0.20
Requires-Dist: lxml<5,>=4.9.3
Requires-Dist: lxml-stubs
Requires-Dist: openpyxl<4,>=3.0.10
Requires-Dist: types-openpyxl
Requires-Dist: numpy==1.26.4
Requires-Dist: pandas<3,>=2.2.2
Requires-Dist: pandas-stubs
Requires-Dist: jinja2<4,>=3.1.2
Requires-Dist: types-requests<3,>=2.32.0
Requires-Dist: rdflib<8,>=7.0.0
Requires-Dist: inflection<6,>=0.5.1
Requires-Dist: validators<1,>=0.28.0
Requires-Dist: requests<3,>=2.32.3
Requires-Dist: jsonschema<5,>=4.22.0
Requires-Dist: types-jsonschema<5,>=4.22
Requires-Dist: translators<6,>=5.9.2
Requires-Dist: charset-normalizer<4,>=3.4.1
Requires-Dist: chardet<6,>=5.2.0
Requires-Dist: beautifulsoup4<5,>=4.12.2
Requires-Dist: markdownify<2,>=1.2.2
Requires-Dist: types-python-dateutil<3,>=2.9
Provides-Extra: dev
Requires-Dist: bandit==1.7.*; extra == "dev"
Requires-Dist: black==24.*; extra == "dev"
Requires-Dist: build==1.1.*; extra == "dev"
Requires-Dist: flake8==7.*; extra == "dev"
Requires-Dist: isort==5.*; extra == "dev"
Requires-Dist: mypy==1.11.*; extra == "dev"
Requires-Dist: pytest==8.*; extra == "dev"
Requires-Dist: pytest-cov==5.*; extra == "dev"
Requires-Dist: twine==5.*; extra == "dev"
Dynamic: author
Dynamic: classifier
Dynamic: description
Dynamic: description-content-type
Dynamic: home-page
Dynamic: license
Dynamic: license-file
Dynamic: provides-extra
Dynamic: requires-dist
Dynamic: requires-python
Dynamic: summary
